README.md
setup.py
nanobt/__init__.py
nanobt/backtesting.py
nanobt/trades.py
nanobt.egg-info/PKG-INFO
nanobt.egg-info/SOURCES.txt
nanobt.egg-info/dependency_links.txt
nanobt.egg-info/top_level.txt
nanobt/examples/__init__.py
nanobt/examples/buy_and_hold.py
nanobt/examples/ema.py