Metadata-Version: 2.1
Name: nanobt
Version: 0.1.1
Summary: A quickly backtesting library for inversion strategies
Home-page: https://github.com/mgarcia0094/nanobt
Author: Miguel Ángel García Gandía
Author-email: mgarcia0094@gmail.com
License: UNKNOWN
Platform: UNKNOWN
Classifier: Programming Language :: Python :: 3
Classifier: License :: OSI Approved :: MIT License
Classifier: Operating System :: OS Independent
Requires-Python: >=3.6
